{
    "craftingStations": [
		{
			"name": "by-hand",
			"displayName": "By Hand"
		},
        {
			"name": "work-bench",
			"displayName": "Work Bench"
		},
		{
			"name": "furnace",
			"displayName": "Furnace"
		},
		{
			"name": "hellforge",
			"displayName": "Hellforge"
		},
		{
			"name": "anvil",
			"displayName": "Iron/Lead Anvil"
		},
        {
            "name": "placed-bottle",
            "displayName": "Placed Bottle/Alchemy Table"
        },
        {
            "name": "water",
            "displayName": "Water/Sink"
        },
        {
			"name": "sawmill",
			"displayName": "Sawmill"
		},
        {
			"name": "loom",
			"displayName": "Loom"
		},
		{
			"name": "table-and-chair",
			"displayName": "Table and Chair"
		},
		{
			"name": "work-bench-and-chair",
			"displayName": "Work Bench and Chair"
		},
        {
			"name": "cooking-pot",
			"displayName": "Cooking Pot"
		},
		{
			"name": "tinkerers-workshop",
			"displayName": "Tinkerer's Workshop"
		},
        {
			"name": "imbuing-station",
			"displayName": "Imbuing Station"
		},
        {
			"name": "dye-vat",
			"displayName": "Dye Vat"
		},
        {
			"name": "heavy-work-bench",
			"displayName": "Heavy Work Bench"
		},
		{
			"name": "altar",
			"displayName": "Demon/Crimson Altar"
		},
		{
			"name": "hardmode-anvil",
			"displayName": "Mythril/Orichalcum Anvil"
		},
		{
			"name": "hardmode-forge",
			"displayName": "Adamantite/Titanium Forge"
		},
        {
			"name": "bookcase",
			"displayName": "Bookcase"
		},
		{
			"name": "crystal-ball",
			"displayName": "Crystal Ball"
		},
		{
			"name": "autohammer",
			"displayName": "Autohammer"
		},
		{
			"name": "ancient-manipulator",
			"displayName": "Ancient Manipulator"
		},
        {
			"name": "honey",
			"displayName": "Honey"
		},
        {
			"name": "draedons-forge",
			"displayName": "Draedon's Forge"
		},
        {
			"name": "thorium-anvil",
			"displayName": "Thorium Anvil"
		},
        {
			"name": "arcane-armor-fabricator",
			"displayName": "Arcane Armor Fabricator"
		},
        {
			"name": "soul-forge",
			"displayName": "Soul Forge"
		},
        {
			"name": "oblivion-forge",
			"displayName": "Oblivion Forge"
		},
        {
			"name": "flarium-forge",
			"displayName": "Flarium Forge"
		},
        {
			"name": "flarium-anvil",
			"displayName": "Flarium Anvil"
		},
        {
			"name": "tiridium-infuser",
			"displayName": "Tiridium Infuser"
		},
        {
			"name": "crucible-of-the-cosmos",
			"displayName": "Crucible of the Cosmos"
		}
	],
    "selectableItems": [
        {
            "name": "ankh-shield",
            "displayName": "Ankh Shield",
            "modName": "Terraria",
            "itemSpacing": [150, 300, 450]
        },
        {
            "name": "cell-phone",
            "displayName": "Cell Phone",
            "modName": "Terraria",
            "itemSpacing": [150, 300, 450, 500, 600, 750, 850, 1000]
        },
        {
            "name": "terraspark-boots",
            "displayName": "Terraspark Boots",
            "modName": "Terraria",
            "itemSpacing": [150, 300, 450, 580, 670]
        },
        {
            "name": "zenith",
            "displayName": "Zenith",
            "modName": "Terraria",
            "itemSpacing": [380, 575, 760, 960, 1160, 1340, 1520]
        },
        {
            "name": "zenith",
            "displayName": "Soul of Eternity (no mod add-ons)",
            "modName": "Fargo's Soul Mod",
            "itemSpacing": 250
        },
        {
            "name": "zenith",
            "displayName": "Soul of Eternity (all mod add-ons)",
            "modName": "Fargo's Soul Mod",
            "itemSpacing": 250
        },
        {
            "name": "auric-tesla-armor",
            "displayName": "Auric Tesla Armour",
            "modName": "Calamity",
            "itemSpacing": [485, 645, 805, 965]
        },
        {
            "name": "zenith",
            "displayName": "Ark of the Cosmos",
            "modName": "Calamity",
            "itemSpacing": 250
        },
        {
            "name": "zenith",
            "displayName": "Celestial Tracers",
            "modName": "Calamity",
            "itemSpacing": 250
        },
        {
            "name": "zenith",
            "displayName": "Celestus",
            "modName": "Calamity",
            "itemSpacing": 250
        },
        {
            "name": "zenith",
            "displayName": "Cosmic Immaterializer",
            "modName": "Calamity",
            "itemSpacing": 250
        },
        {
            "name": "zenith",
            "displayName": "Devil's Devastation",
            "modName": "Calamity",
            "itemSpacing": 250
        },
        {
            "name": "zenith",
            "displayName": "Drataliornus",
            "modName": "Calamity",
            "itemSpacing": 250
        },
        {
            "name": "zenith",
            "displayName": "Eclipse Mirror",
            "modName": "Calamity",
            "itemSpacing": 250
        },
        {
            "name": "zenith",
            "displayName": "Eternity",
            "modName": "Calamity",
            "itemSpacing": 250
        },
        {
            "name": "zenith",
            "displayName": "Ethereal Talisman",
            "modName": "Calamity",
            "itemSpacing": 250
        },
        {
            "name": "zenith",
            "displayName": "Exo Gladius",
            "modName": "Calamity",
            "itemSpacing": 250
        },
        {
            "name": "zenith",
            "displayName": "Exoblade",
            "modName": "Calamity",
            "itemSpacing": 250
        },
        {
            "name": "zenith",
            "displayName": "Magnomaly Cannon",
            "modName": "Calamity",
            "itemSpacing": 250
        },
        {
            "name": "zenith",
            "displayName": "Nanotech",
            "modName": "Calamity",
            "itemSpacing": 250
        },
        {
            "name": "zenith",
            "displayName": "Nucleogenesis",
            "modName": "Calamity",
            "itemSpacing": 250
        },
        {
            "name": "zenith",
            "displayName": "Photoviscerator",
            "modName": "Calamity",
            "itemSpacing": 250
        },
        {
            "name": "rampart-of-deities",
            "displayName": "Rampart of Deities",
            "modName": "Calamity",
            "itemSpacing": [175, 320, 465]
        },
        {
            "name": "the-sponge",
            "displayName": "The Sponge",
            "modName": "Calamity",
            "itemSpacing": [215, 410, 600, 750, 900, 1050]
        },
        {
            "name": "zenith",
            "displayName": "Supernova",
            "modName": "Calamity",
            "itemSpacing": 250
        },
        {
            "name": "zenith",
            "displayName": "Vivid Clarity",
            "modName": "Calamity",
            "itemSpacing": 250
        },
        {
            "name": "zenith",
            "displayName": "Celestial Edge Pandolarra",
            "modName": "Shadows of Abaddon",
            "itemSpacing": 250
        },
        {
            "name": "zenith",
            "displayName": "Cosmic Desolation",
            "modName": "Shadows of Abaddon",
            "itemSpacing": 250
        },
        {
            "name": "zenith",
            "displayName": "The Leviathan III",
            "modName": "Shadows of Abaddon",
            "itemSpacing": 250
        },
        {
            "name": "zenith",
            "displayName": "Memento Mori",
            "modName": "Shadows of Abaddon",
            "itemSpacing": 250
        },
        {
            "name": "zenith",
            "displayName": "Moon Edged Cold Front",
            "modName": "Shadows of Abaddon",
            "itemSpacing": 250
        },
        {
            "name": "zenith",
            "displayName": "Shield of Reflections",
            "modName": "Shadows of Abaddon",
            "itemSpacing": 250
        },
        {
            "name": "zenith",
            "displayName": "Warp Tracers",
            "modName": "Shadows of Abaddon",
            "itemSpacing": 250
        },
        {
            "name": "zenith",
            "displayName": "Terrarium Defender",
            "modName": "Thorium",
            "itemSpacing": 250
        },
        {
            "name": "zenith",
            "displayName": "Terrarium Particle Sprinters",
            "modName": "Throium",
            "itemSpacing": 250
        }
    ]
}
